texbox/__init__.py
texbox/cli_acronyms.py
texbox/cli_tables.py
texbox/constants.py
texbox/parser.py
texbox/utils.py
texbox-0.2.1.dist-info/LICENSE
texbox-0.2.1.dist-info/METADATA
texbox-0.2.1.dist-info/WHEEL
texbox-0.2.1.dist-info/entry_points.txt
texbox-0.2.1.dist-info/top_level.txt
texbox-0.2.1.dist-info/RECORD
