Metadata-Version: 2.1
Name: texbox
Version: 0.2.1
Summary: An opinionated Python CLI to create, organize, and prettify specific files of a LaTeX project.
Home-page: https://github.com/joaopalmeiro/texbox
Author: João Palmeiro
Author-email: jm.palmeiro@campus.fct.unl.pt
License: MIT
Project-URL: Bug Reports, https://github.com/joaopalmeiro/texbox/issues
Project-URL: Source, https://github.com/joaopalmeiro/texbox
Keywords: cli,refactor,sort,prettify,acronyms,latex
Platform: UNKNOWN
Classifier: Development Status :: 3 - Alpha
Classifier: Environment :: Console
Classifier: Intended Audience :: Science/Research
Classifier: License :: OSI Approved :: MIT License
Classifier: Natural Language :: English
Classifier: Programming Language :: Python
Classifier: Programming Language :: Python :: 3
Classifier: Programming Language :: Python :: 3 :: Only
Classifier: Programming Language :: Python :: 3.6
Classifier: Programming Language :: Python :: 3.7
Classifier: Programming Language :: Python :: 3.8
Classifier: Programming Language :: Python :: Implementation :: CPython
Classifier: Topic :: Software Development :: Libraries
Classifier: Topic :: Software Development :: Libraries :: Python Modules
Classifier: Topic :: Software Development :: Quality Assurance
Classifier: Topic :: Terminals
Classifier: Topic :: Text Processing :: Markup :: LaTeX
Classifier: Topic :: Utilities
Classifier: Typing :: Typed
Requires-Python: >=3.6, <=3.8
Requires-Dist: pyparsing
Requires-Dist: pandas
